virtualkeys/__init__.py
virtualkeys-0.dist-info/METADATA
virtualkeys-0.dist-info/WHEEL
virtualkeys-0.dist-info/top_level.txt
virtualkeys-0.dist-info/RECORD
