Metadata-Version: 2.1
Name: virtualkeys
Version: 0
Summary: Cross-platform Win32 virtual-key codes
Home-page: https://gist.github.com/biqqles/31d1611d23e76b0b7c59d203c0004798
Author: biqqles
Author-email: biqqles@protonmail.com
License: UNKNOWN
Platform: UNKNOWN
